{"header":{"type":"esearch","version":"0.3"},"esearchresult":{"count":"0","retmax":"0","retstart":"0","querykey":"1","webenv":"MCID_6a602f7bd4411bdae2054ef3","idlist":[],"translationset":[],"querytranslation":"\"Narcolepsy and hypersomnia in Norwegian children and young adults following the influenza A(H1N1) 2009 pandemic\"[Title]","warninglist":{"phrasesignored":[],"quotedphrasesnotfound":["\"Narcolepsy and hypersomnia in Norwegian children and young adults following the influenza A(H1N1) 2009 pandemic\"[Title]"],"outputmessages":["No items found."]}}}
