{"header":{"type":"esearch","version":"0.3"},"esearchresult":{"count":"0","retmax":"0","retstart":"0","querykey":"1","webenv":"MCID_6a6030096566f0262409ceac","idlist":[],"translationset":[],"querytranslation":"\"Optimized Neural Network Based on Genetic Algorithm to Construct Hand-Foot-and-Mouth Disease Prediction and Early-Warning Model\"[Title]","warninglist":{"phrasesignored":[],"quotedphrasesnotfound":["\"Optimized Neural Network Based on Genetic Algorithm to Construct Hand-Foot-and-Mouth Disease Prediction and Early-Warning Model\"[Title]"],"outputmessages":["No items found."]}}}
