<?xml version="1.0" ?>
<!DOCTYPE PubmedArticleSet PUBLIC "-//NLM//DTD PubMedArticle, 1st January 2025//EN" "https://dtd.nlm.nih.gov/ncbi/pubmed/out/pubmed_250101.dtd">
<PubmedArticleSet>
<PubmedArticle><MedlineCitation Status="MEDLINE" Owner="NLM" IndexingMethod="Manual"><PMID Version="1">23383591</PMID><DateCompleted><Year>2015</Year><Month>04</Month><Day>02</Day></DateCompleted><DateRevised><Year>2013</Year><Month>05</Month><Day>28</Day></DateRevised><Article PubModel="Print-Electronic"><Journal><ISSN IssnType="Electronic">1360-0451</ISSN><JournalIssue CitedMedium="Internet"><Volume>25</Volume><Issue>6</Issue><PubDate><Year>2013</Year></PubDate></JournalIssue><Title>AIDS care</Title><ISOAbbreviation>AIDS Care</ISOAbbreviation></Journal><ArticleTitle>Estimating the number of HIV-positive pregnant women in Sergipe, Brazil, using capture-recapture.</ArticleTitle><Pagination><StartPage>691</StartPage><EndPage>694</EndPage><MedlinePgn>691-4</MedlinePgn></Pagination><ELocationID EIdType="doi" ValidYN="Y">10.1080/09540121.2013.764389</ELocationID><Abstract><AbstractText>The objective of the study was to estimate the population of HIV-seropositive pregnant women in the State of Sergipe between 2000 and 2010, using the capture-recapture method (CRC). Three databases were used as independent lists: The Brazilian Case Registry Database (SINAN), Laboratory Test Control System (SISCEL) and medical data records of the STD/HIV/AIDS service of Sergipe (CEMAR). For analysis, a log-linear regression model was used to ascertain the total population size. We identified 729 HIV-seropositive pregnant women from the three lists. Among them, only 317 (43.5%) were included in SINAN, 646 (88.6%) were included in SISCEL and 274 (37.6%) appeared in the CEMAR database. Using CRC, we estimated that there were in total 1110 HIV-seropositive pregnant women; therefore, 381 (34.3%) women were not captured by any of the three systems. The CRC method is a potentially useful and important tool in the evaluation of official reporting systems in Brazil.</AbstractText></Abstract><AuthorList CompleteYN="Y"><Author ValidYN="Y"><LastName>de Lemos</LastName><ForeName>L&#xed;gia Mara Dolce</ForeName><Initials>LM</Initials><AffiliationInfo><Affiliation>Department of Nursing, Federal University of Sergipe Brazil. ligiadolce@gmail.com</Affiliation></AffiliationInfo></Author><Author ValidYN="Y"><LastName>Duarte</LastName><ForeName>Gabriella Souza</ForeName><Initials>GS</Initials></Author><Author ValidYN="Y"><LastName>Martins</LastName><ForeName>N&#xe1;gyla Galv&#xe3;o Regis</ForeName><Initials>NG</Initials></Author><Author ValidYN="Y"><LastName>da Silva</LastName><ForeName>Fl&#xe1;via Jan&#xf3;lio Costacurta Pinto</ForeName><Initials>FJ</Initials></Author><Author ValidYN="Y"><LastName>Ilozue</LastName><ForeName>Chinenye</ForeName><Initials>C</Initials></Author><Author ValidYN="Y"><LastName>Gurgel</LastName><ForeName>Ricardo Queiroz</ForeName><Initials>RQ</Initials></Author></AuthorList><Language>eng</Language><PublicationTypeList><PublicationType UI="D016428">Journal Article</PublicationType></PublicationTypeList><ArticleDate DateType="Electronic"><Year>2013</Year><Month>02</Month><Day>05</Day></ArticleDate></Article><MedlineJournalInfo><Country>England</Country><MedlineTA>AIDS Care</MedlineTA><NlmUniqueID>8915313</NlmUniqueID><ISSNLinking>0954-0121</ISSNLinking></MedlineJournalInfo><CitationSubset>IM</CitationSubset><MeshHeadingList><MeshHeading><DescriptorName UI="D000293" MajorTopicYN="N">Adolescent</DescriptorName></MeshHeading><MeshHeading><DescriptorName UI="D000328" MajorTopicYN="N">Adult</DescriptorName></MeshHeading><MeshHeading><DescriptorName UI="D001938" MajorTopicYN="N" Type="Geographic">Brazil</DescriptorName><QualifierName UI="Q000453" MajorTopicYN="N">epidemiology</QualifierName></MeshHeading><MeshHeading><DescriptorName UI="D005260" MajorTopicYN="N">Female</DescriptorName></MeshHeading><MeshHeading><DescriptorName UI="D015658" MajorTopicYN="N">HIV Infections</DescriptorName><QualifierName UI="Q000453" MajorTopicYN="Y">epidemiology</QualifierName></MeshHeading><MeshHeading><DescriptorName UI="D006801" MajorTopicYN="N">Humans</DescriptorName></MeshHeading><MeshHeading><DescriptorName UI="D018445" MajorTopicYN="N">Infectious Disease Transmission, Vertical</DescriptorName></MeshHeading><MeshHeading><DescriptorName UI="D007256" MajorTopicYN="N">Information Systems</DescriptorName></MeshHeading><MeshHeading><DescriptorName UI="D008498" MajorTopicYN="N">Medical Record Linkage</DescriptorName></MeshHeading><MeshHeading><DescriptorName UI="D008875" MajorTopicYN="N">Middle Aged</DescriptorName></MeshHeading><MeshHeading><DescriptorName UI="D011247" MajorTopicYN="N">Pregnancy</DescriptorName></MeshHeading><MeshHeading><DescriptorName UI="D012042" MajorTopicYN="N">Registries</DescriptorName><QualifierName UI="Q000706" MajorTopicYN="Y">statistics &amp; numerical data</QualifierName></MeshHeading><MeshHeading><DescriptorName UI="D018571" MajorTopicYN="Y">Sentinel Surveillance</DescriptorName></MeshHeading><MeshHeading><DescriptorName UI="D055815" MajorTopicYN="N">Young Adult</DescriptorName></MeshHeading></MeshHeadingList></MedlineCitation><PubmedData><History><PubMedPubDate PubStatus="entrez"><Year>2013</Year><Month>2</Month><Day>7</Day><Hour>6</Hour><Minute>0</Minute></PubMedPubDate><PubMedPubDate PubStatus="pubmed"><Year>2013</Year><Month>2</Month><Day>7</Day><Hour>6</Hour><Minute>0</Minute></PubMedPubDate><PubMedPubDate PubStatus="medline"><Year>2015</Year><Month>4</Month><Day>4</Day><Hour>6</Hour><Minute>0</Minute></PubMedPubDate></History><PublicationStatus>ppublish</PublicationStatus><ArticleIdList><ArticleId IdType="pubmed">23383591</ArticleId><ArticleId IdType="doi">10.1080/09540121.2013.764389</ArticleId></ArticleIdList></PubmedData></PubmedArticle></PubmedArticleSet>