<?xml version="1.0" ?>
<!DOCTYPE PubmedArticleSet PUBLIC "-//NLM//DTD PubMedArticle, 1st January 2025//EN" "https://dtd.nlm.nih.gov/ncbi/pubmed/out/pubmed_250101.dtd">
<PubmedArticleSet>
<PubmedArticle><MedlineCitation Status="MEDLINE" Owner="NLM" IndexingMethod="Automated"><PMID Version="1">32634822</PMID><DateCompleted><Year>2021</Year><Month>01</Month><Day>27</Day></DateCompleted><DateRevised><Year>2025</Year><Month>05</Month><Day>30</Day></DateRevised><Article PubModel="Print"><Journal><ISSN IssnType="Electronic">1537-6591</ISSN><JournalIssue CitedMedium="Internet"><Volume>72</Volume><Issue>1</Issue><PubDate><Year>2021</Year><Month>Jan</Month><Day>23</Day></PubDate></JournalIssue><Title>Clinical infectious diseases : an official publication of the Infectious Diseases Society of America</Title><ISOAbbreviation>Clin Infect Dis</ISOAbbreviation></Journal><ArticleTitle>Development and Delivery of a Real-time Hospital-onset COVID-19 Surveillance System Using Network Analysis.</ArticleTitle><Pagination><StartPage>82</StartPage><EndPage>89</EndPage><MedlinePgn>82-89</MedlinePgn></Pagination><ELocationID EIdType="doi" ValidYN="Y">10.1093/cid/ciaa892</ELocationID><Abstract><AbstractText Label="BACKGROUND">Understanding nosocomial acquisition, outbreaks, and transmission chains in real time will be fundamental to ensuring infection-prevention measures are effective in controlling coronavirus disease 2019 (COVID-19) in healthcare. We report the design and implementation of a hospital-onset COVID-19 infection (HOCI) surveillance system for an acute healthcare setting to target prevention interventions.</AbstractText><AbstractText Label="METHODS">The study took place in a large teaching hospital group in London, United Kingdom. All patients tested for SARS-CoV-2 between 4 March and 14 April 2020 were included. Utilizing data routinely collected through electronic healthcare systems we developed a novel surveillance system for determining and reporting HOCI incidence and providing real-time network analysis. We provided daily reports on incidence and trends over time to support HOCI investigation and generated geotemporal reports using network analysis to interrogate admission pathways for common epidemiological links to infer transmission chains. By working with stakeholders the reports were co-designed for end users.</AbstractText><AbstractText Label="RESULTS">Real-time surveillance reports revealed changing rates of HOCI throughout the course of the COVID-19 epidemic, key wards fueling probable transmission events, HOCIs overrepresented in particular specialties managing high-risk patients, the importance of integrating analysis of individual prior pathways, and the value of co-design in producing data visualization. Our surveillance system can effectively support national surveillance.</AbstractText><AbstractText Label="CONCLUSIONS">Through early analysis of the novel surveillance system we have provided a description of HOCI rates and trends over time using real-time shifting denominator data. We demonstrate the importance of including the analysis of patient pathways and networks in characterizing risk of transmission and targeting infection-control interventions.</AbstractText><CopyrightInformation>&#xa9; The Author(s) 2020. Published by Oxford University Press for the Infectious Diseases Society of America.</CopyrightInformation></Abstract><AuthorList CompleteYN="Y"><Author ValidYN="Y"><LastName>Price</LastName><ForeName>James Richard</ForeName><Initials>JR</Initials><AffiliationInfo><Affiliation>National Institute for Health Research Health Protection Research Unit in HCAI and AMR, Imperial College London, London, United Kingdom.</Affiliation></AffiliationInfo></Author><Author ValidYN="Y"><LastName>Mookerjee</LastName><ForeName>Siddharth</ForeName><Initials>S</Initials><AffiliationInfo><Affiliation>National Institute for Health Research Health Protection Research Unit in HCAI and AMR, Imperial College London, London, United Kingdom.</Affiliation></AffiliationInfo></Author><Author ValidYN="Y"><LastName>Dyakova</LastName><ForeName>Eleonora</ForeName><Initials>E</Initials><AffiliationInfo><Affiliation>Imperial College Healthcare NHS Trust, Imperial College London, London, United Kingdom.</Affiliation></AffiliationInfo></Author><Author ValidYN="Y"><LastName>Myall</LastName><ForeName>Ashleigh</ForeName><Initials>A</Initials><AffiliationInfo><Affiliation>National Institute for Health Research Health Protection Research Unit in HCAI and AMR, Imperial College London, London, United Kingdom.</Affiliation></AffiliationInfo><AffiliationInfo><Affiliation>Department of Mathematics, Imperial College London, London, United Kingdom.</Affiliation></AffiliationInfo></Author><Author ValidYN="Y"><LastName>Leung</LastName><ForeName>Wendy</ForeName><Initials>W</Initials><AffiliationInfo><Affiliation>Imperial College Healthcare NHS Trust, Imperial College London, London, United Kingdom.</Affiliation></AffiliationInfo></Author><Author ValidYN="Y"><LastName>Wei&#xdf;e</LastName><ForeName>Andrea Yeong</ForeName><Initials>AY</Initials><AffiliationInfo><Affiliation>National Institute for Health Research Health Protection Research Unit in HCAI and AMR, Imperial College London, London, United Kingdom.</Affiliation></AffiliationInfo></Author><Author ValidYN="Y"><LastName>Shersing</LastName><ForeName>Yeeshika</ForeName><Initials>Y</Initials><AffiliationInfo><Affiliation>Imperial College Healthcare NHS Trust, Imperial College London, London, United Kingdom.</Affiliation></AffiliationInfo></Author><Author ValidYN="Y"><LastName>Brannigan</LastName><ForeName>Eimear Therese</ForeName><Initials>ET</Initials><AffiliationInfo><Affiliation>Imperial College Healthcare NHS Trust, Imperial College London, London, United Kingdom.</Affiliation></AffiliationInfo></Author><Author ValidYN="Y"><LastName>Galletly</LastName><ForeName>Tracey</ForeName><Initials>T</Initials><AffiliationInfo><Affiliation>Imperial College Healthcare NHS Trust, Imperial College London, London, United Kingdom.</Affiliation></AffiliationInfo></Author><Author ValidYN="Y"><LastName>Muir</LastName><ForeName>David</ForeName><Initials>D</Initials><AffiliationInfo><Affiliation>Imperial College Healthcare NHS Trust, Imperial College London, London, United Kingdom.</Affiliation></AffiliationInfo></Author><Author ValidYN="Y"><LastName>Randell</LastName><ForeName>Paul</ForeName><Initials>P</Initials><AffiliationInfo><Affiliation>Imperial College Healthcare NHS Trust, Imperial College London, London, United Kingdom.</Affiliation></AffiliationInfo></Author><Author ValidYN="Y"><LastName>Davies</LastName><ForeName>Frances</ForeName><Initials>F</Initials><AffiliationInfo><Affiliation>Imperial College Healthcare NHS Trust, Imperial College London, London, United Kingdom.</Affiliation></AffiliationInfo></Author><Author ValidYN="Y"><LastName>Bolt</LastName><ForeName>Frances</ForeName><Initials>F</Initials><AffiliationInfo><Affiliation>National Institute for Health Research Health Protection Research Unit in HCAI and AMR, Imperial College London, London, United Kingdom.</Affiliation></AffiliationInfo></Author><Author ValidYN="Y"><LastName>Barahona</LastName><ForeName>Mauricio</ForeName><Initials>M</Initials><AffiliationInfo><Affiliation>Department of Mathematics, Imperial College London, London, United Kingdom.</Affiliation></AffiliationInfo></Author><Author ValidYN="Y"><LastName>Otter</LastName><ForeName>Jonathan Ashley</ForeName><Initials>JA</Initials><AffiliationInfo><Affiliation>National Institute for Health Research Health Protection Research Unit in HCAI and AMR, Imperial College London, London, United Kingdom.</Affiliation></AffiliationInfo></Author><Author ValidYN="Y"><LastName>Holmes</LastName><ForeName>Alison H</ForeName><Initials>AH</Initials><AffiliationInfo><Affiliation>National Institute for Health Research Health Protection Research Unit in HCAI and AMR, Imperial College London, London, United Kingdom.</Affiliation></AffiliationInfo></Author></AuthorList><Language>eng</Language><GrantList CompleteYN="Y"><Grant><GrantID>MR/T005254/1</GrantID><Acronym>MRC_</Acronym><Agency>Medical Research Council</Agency><Country>United Kingdom</Country></Grant><Grant><GrantID>MRF-145-0004-TPG-AVISO</GrantID><Acronym>MRF_</Acronym><Agency>MRF_</Agency><Country>United Kingdom</Country></Grant></GrantList><PublicationTypeList><PublicationType UI="D016428">Journal Article</PublicationType><PublicationType UI="D013485">Research Support, Non-U.S. Gov't</PublicationType></PublicationTypeList></Article><MedlineJournalInfo><Country>United States</Country><MedlineTA>Clin Infect Dis</MedlineTA><NlmUniqueID>9203213</NlmUniqueID><ISSNLinking>1058-4838</ISSNLinking></MedlineJournalInfo><CitationSubset>IM</CitationSubset><MeshHeadingList><MeshHeading><DescriptorName UI="D000086382" MajorTopicYN="Y">COVID-19</DescriptorName></MeshHeading><MeshHeading><DescriptorName UI="D006761" MajorTopicYN="N">Hospitals</DescriptorName></MeshHeading><MeshHeading><DescriptorName UI="D006801" MajorTopicYN="N">Humans</DescriptorName></MeshHeading><MeshHeading><DescriptorName UI="D008131" MajorTopicYN="N" Type="Geographic">London</DescriptorName></MeshHeading><MeshHeading><DescriptorName UI="D000086402" MajorTopicYN="N">SARS-CoV-2</DescriptorName></MeshHeading><MeshHeading><DescriptorName UI="D006113" MajorTopicYN="N" Type="Geographic">United Kingdom</DescriptorName></MeshHeading></MeshHeadingList><KeywordList Owner="NOTNLM"><Keyword MajorTopicYN="N">COVID-19</Keyword><Keyword MajorTopicYN="N">SARS-Cov-2</Keyword><Keyword MajorTopicYN="N">hospital-onset infection</Keyword><Keyword MajorTopicYN="N">network analysis</Keyword><Keyword MajorTopicYN="N">surveillance</Keyword></KeywordList></MedlineCitation><PubmedData><History><PubMedPubDate PubStatus="received"><Year>2020</Year><Month>6</Month><Day>16</Day></PubMedPubDate><PubMedPubDate PubStatus="pubmed"><Year>2020</Year><Month>7</Month><Day>8</Day><Hour>6</Hour><Minute>0</Minute></PubMedPubDate><PubMedPubDate PubStatus="medline"><Year>2021</Year><Month>1</Month><Day>28</Day><Hour>6</Hour><Minute>0</Minute></PubMedPubDate><PubMedPubDate PubStatus="entrez"><Year>2020</Year><Month>7</Month><Day>8</Day><Hour>6</Hour><Minute>0</Minute></PubMedPubDate><PubMedPubDate PubStatus="pmc-release"><Year>2020</Year><Month>7</Month><Day>7</Day></PubMedPubDate></History><PublicationStatus>ppublish</PublicationStatus><ArticleIdList><ArticleId IdType="pubmed">32634822</ArticleId><ArticleId IdType="pmc">PMC7454383</ArticleId><ArticleId IdType="doi">10.1093/cid/ciaa892</ArticleId><ArticleId IdType="pii">5868508</ArticleId></ArticleIdList><ReferenceList><Reference><Citation>
World Health Organization. Coronavirus disease (COVID-19) situation report&#x2014;139. Available at: https://www.who.int/emergencies/diseases/novel-coronavirus-2019/situation-reports. Accessed 6 June 2020.</Citation></Reference><Reference><Citation>
European Centre for Disease Prevention and Control. COVID-19 situation update worldwide, as of 24 May 2020. Available at: https://www.ecdc.europa.eu/en/geographical-distribution-2019-ncov-cases. Accessed 24 May 2020.</Citation></Reference><Reference><Citation>
Centers for Disease Control and Prevention. A weekly summary of U.S. COVID-19 hospitalization data: laboratory-confirmed COVID-19-associated hospitalizations (COVID-NET). Available at: https://gis.cdc.gov/grasp/COVIDNet/COVID19_3.html. Accessed 4 May 2020.</Citation></Reference><Reference><Citation>Docherty AB, Harrison EM, Green CA, et al. ; ISARIC4C Investigators Features of 20&#x2009;133 UK patients in hospital with covid-19 using the ISARIC WHO Clinical Characterisation Protocol: prospective observational cohort study. BMJ 2020; 369:m1985.</Citation><ArticleIdList><ArticleId IdType="pmc">PMC7243036</ArticleId><ArticleId IdType="pubmed">32444460</ArticleId></ArticleIdList></Reference><Reference><Citation>Schwierzeck V, Konig JC, Kuhn J, et al. First reported nosocomial outbreak of severe acute respiratory syndrome coronavirus 2 (SARS-CoV-2) in a pediatric dialysis unit. Clin Infect Dis 2020; ciaa491. doi: 10.1093/cid/ciaa491. Online ahead of print.</Citation><ArticleIdList><ArticleId IdType="doi">10.1093/cid/ciaa491</ArticleId><ArticleId IdType="pmc">PMC7197625</ArticleId><ArticleId IdType="pubmed">33501962</ArticleId></ArticleIdList></Reference><Reference><Citation>Wang X, Zhou Q, He Y, et al. Nosocomial outbreak of 2019 novel coronavirus pneumonia in Wuhan, China. Eur Respir J 2020; 55: 2000544. doi: 10.1183/13993003.00544-2020</Citation><ArticleIdList><ArticleId IdType="doi">10.1183/13993003.00544-2020</ArticleId><ArticleId IdType="pmc">PMC7236818</ArticleId><ArticleId IdType="pubmed">32366488</ArticleId></ArticleIdList></Reference><Reference><Citation>Lauer SA, Grantz KH, Bi Q, et al. The incubation period of coronavirus disease 2019 (COVID-19) from publicly reported confirmed cases: estimation and application. Ann Intern Med 2020; 172: 577&#x2013; 82.</Citation><ArticleIdList><ArticleId IdType="pmc">PMC7081172</ArticleId><ArticleId IdType="pubmed">32150748</ArticleId></ArticleIdList></Reference><Reference><Citation>Treibel TA, Manisty C, Burton M, et al. COVID-19: PCR screening of asymptomatic health-care workers at London hospital. Lancet 2020; 395:1608&#x2013;10.</Citation><ArticleIdList><ArticleId IdType="pmc">PMC7206444</ArticleId><ArticleId IdType="pubmed">32401714</ArticleId></ArticleIdList></Reference><Reference><Citation>Phua J, Weng L, Ling L, et al. Intensive care management of coronavirus disease 2019 (COVID-19): challenges and recommendations. Lancet Respir Med 2020; 8:506&#x2013;17.</Citation><ArticleIdList><ArticleId IdType="pmc">PMC7198848</ArticleId><ArticleId IdType="pubmed">32272080</ArticleId></ArticleIdList></Reference><Reference><Citation>Lacobucci G. Covid-19: doctors sound alarm over hospital transmissions. BMJ 2020; 369:m2013.</Citation><ArticleIdList><ArticleId IdType="pubmed">32430304</ArticleId></ArticleIdList></Reference><Reference><Citation>
European Centre for Disease Prevention and Control. Technical report: strategies for the surveillance of COVID-19.2020.  Available at: https://www.ecdc.europa.eu/sites/default/files/documents/COVID-19-surveillance-strategy-9-Apr-2020.pdf. Accessed 9 April 2020.</Citation></Reference><Reference><Citation>Garg S, Kim L, Whitaker M, et al. Hospitalization rates and characteristics of patients hospitalized with laboratory-confirmed coronavirus disease 2019&#x2014;COVID-NET, 14 states, March 1-30, 2020. MMWR Morb Mortal Wkly Rep 2020; 69:458&#x2013;64.</Citation><ArticleIdList><ArticleId IdType="pmc">PMC7755063</ArticleId><ArticleId IdType="pubmed">32298251</ArticleId></ArticleIdList></Reference><Reference><Citation>
NHS England and NHS Improvement. Operating framework for urgent and planned services within hospitals. Available at: https://covidlawlab.org/wp-content/uploads/2020/06/Operating-framework-for-urgent-and-planned-services-within-hospitals.pdf. Accessed 15 June 2020.</Citation></Reference><Reference><Citation>Meredith LW, Hamilton WL, Warne B, et al. Rapid implementation of SARS-CoV-2 sequencing to investigate cases of health-care associated COVID-19: a prospective genomic surveillance study. Lancet Infect Dis 2020.</Citation><ArticleIdList><ArticleId IdType="pmc">PMC7806511</ArticleId><ArticleId IdType="pubmed">32679081</ArticleId></ArticleIdList></Reference><Reference><Citation>
Public Health England. 
COVID-19: investigation and initial clinical management of possible cases. 2020. Available at: https://www.gov.uk/government/publications/wuhan-novel-coronavirus-initial-investigation-of-possible-cases/investigation-and-initial-clinical-management-of-possible-cases-of-wuhan-novel-coronavirus-wn-cov-infection. Accessed 4 May 2020..</Citation></Reference><Reference><Citation>van Kleef E, Robotham JV, Jit M, Deeny SR, Edmunds WJ. Modelling the transmission of healthcare associated infections: a systematic review. BMC Infect Dis 2013; 13:294.</Citation><ArticleIdList><ArticleId IdType="pmc">PMC3701468</ArticleId><ArticleId IdType="pubmed">23809195</ArticleId></ArticleIdList></Reference><Reference><Citation>Rivett L, Sridhar S, Sparkes D, et al. Screening of healthcare workers for SARS-CoV-2 highlights the role of asymptomatic carriage in COVID-19 transmission. Elife 2020; 9: e58728. doi: 10.7554/eLife.58728.</Citation><ArticleIdList><ArticleId IdType="doi">10.7554/eLife.58728</ArticleId><ArticleId IdType="pmc">PMC7314537</ArticleId><ArticleId IdType="pubmed">32392129</ArticleId></ArticleIdList></Reference></ReferenceList></PubmedData></PubmedArticle></PubmedArticleSet>