<?xml version="1.0" ?>
<!DOCTYPE PubmedArticleSet PUBLIC "-//NLM//DTD PubMedArticle, 1st January 2025//EN" "https://dtd.nlm.nih.gov/ncbi/pubmed/out/pubmed_250101.dtd">
<PubmedArticleSet>
<PubmedArticle><MedlineCitation Status="MEDLINE" Owner="NLM" IndexingMethod="Automated"><PMID Version="1">33783394</PMID><DateCompleted><Year>2021</Year><Month>05</Month><Day>31</Day></DateCompleted><DateRevised><Year>2023</Year><Month>09</Month><Day>08</Day></DateRevised><Article PubModel="Print"><Journal><ISSN IssnType="Electronic">1531-5487</ISSN><JournalIssue CitedMedium="Internet"><Volume>32</Volume><Issue>3</Issue><PubDate><Year>2021</Year><Month>May</Month><Day>01</Day></PubDate></JournalIssue><Title>Epidemiology (Cambridge, Mass.)</Title><ISOAbbreviation>Epidemiology</ISOAbbreviation></Journal><ArticleTitle>Incorporating Information on Control Diseases Across Space and Time to Improve Estimation of the Population-level Impact of Vaccines.</ArticleTitle><Pagination><StartPage>360</StartPage><EndPage>367</EndPage><MedlinePgn>360-367</MedlinePgn></Pagination><ELocationID EIdType="doi" ValidYN="Y">10.1097/EDE.0000000000001341</ELocationID><Abstract><AbstractText Label="BACKGROUND">The synthetic control method evaluates the impact of vaccines while adjusting for a set of control time series representing diseases that are unaffected by the vaccine. However, noise in control time series, particularly in areas with small counts, can obscure the association with the outcome, preventing proper adjustments. To overcome this issue, we investigated the use of temporal and spatial aggregation methods to smooth the controls and allow for adjustment of underlying trends.</AbstractText><AbstractText Label="METHODS">We evaluated the impact of pneumococcal conjugate vaccine on all-cause pneumonia hospitalizations among adults &#x2265;80 years of age in 25 states in Brazil from 2005 to 2015. Pneumonia hospitalizations in this group indicated a strong increasing secular trend over time that may influence estimation of the vaccine impact. First, we aggregated control time series separately by time or space before incorporation into the synthetic control model. Next, we developed distributed lags models (DLMs) to automatically determine what level of aggregation was most appropriate for each control.</AbstractText><AbstractText Label="RESULTS">The aggregation of control time series enabled the synthetic control model to identify stronger associations between outcome and controls. As a result, the aggregation models and DLMs succeeded in adjusting for long-term trends even in smaller states with sparse data, leading to more reliable estimates of vaccine impact.</AbstractText><AbstractText Label="CONCLUSIONS">When synthetic control struggles to identify important prevaccine associations due to noise in control time series, users can aggregate controls over time or space to generate more robust estimates of the vaccine impact. DLMs automate this process without requiring prespecification of the aggregation level.</AbstractText><CopyrightInformation>Copyright &#xa9; 2021 The Author(s). Published by Wolters Kluwer Health, Inc.</CopyrightInformation></Abstract><AuthorList CompleteYN="Y"><Author ValidYN="Y"><LastName>Shioda</LastName><ForeName>Kayoko</ForeName><Initials>K</Initials><AffiliationInfo><Affiliation>From the Department of Epidemiology of Microbial Diseases, Yale School of Public Health, New Haven, CT.</Affiliation></AffiliationInfo></Author><Author ValidYN="Y"><LastName>Cai</LastName><ForeName>Jiachen</ForeName><Initials>J</Initials><AffiliationInfo><Affiliation>Department of Biostatistics, Yale School of Public Health, New Haven, CT.</Affiliation></AffiliationInfo></Author><Author ValidYN="Y"><LastName>Warren</LastName><ForeName>Joshua L</ForeName><Initials>JL</Initials><AffiliationInfo><Affiliation>Department of Biostatistics, Yale School of Public Health, New Haven, CT.</Affiliation></AffiliationInfo></Author><Author ValidYN="Y"><LastName>Weinberger</LastName><ForeName>Daniel M</ForeName><Initials>DM</Initials><AffiliationInfo><Affiliation>From the Department of Epidemiology of Microbial Diseases, Yale School of Public Health, New Haven, CT.</Affiliation></AffiliationInfo></Author></AuthorList><Language>eng</Language><GrantList CompleteYN="Y"><Grant><GrantID>R01 AI112970</GrantID><Acronym>AI</Acronym><Agency>NIAID NIH HHS</Agency><Country>United States</Country></Grant><Grant><GrantID>R01 AI123208</GrantID><Acronym>AI</Acronym><Agency>NIAID NIH HHS</Agency><Country>United States</Country></Grant><Grant><GrantID>R01 AI137093</GrantID><Acronym>AI</Acronym><Agency>NIAID NIH HHS</Agency><Country>United States</Country></Grant><Grant><GrantID>UL1 TR001863</GrantID><Acronym>TR</Acronym><Agency>NCATS NIH HHS</Agency><Country>United States</Country></Grant></GrantList><PublicationTypeList><PublicationType UI="D016428">Journal Article</PublicationType><PublicationType UI="D052061">Research Support, N.I.H., Extramural</PublicationType><PublicationType UI="D013485">Research Support, Non-U.S. Gov't</PublicationType></PublicationTypeList></Article><MedlineJournalInfo><Country>United States</Country><MedlineTA>Epidemiology</MedlineTA><NlmUniqueID>9009644</NlmUniqueID><ISSNLinking>1044-3983</ISSNLinking></MedlineJournalInfo><ChemicalList><Chemical><RegistryNumber>0</RegistryNumber><NameOfSubstance UI="D022242">Pneumococcal Vaccines</NameOfSubstance></Chemical><Chemical><RegistryNumber>0</RegistryNumber><NameOfSubstance UI="D018074">Vaccines, Conjugate</NameOfSubstance></Chemical></ChemicalList><CitationSubset>IM</CitationSubset><MeshHeadingList><MeshHeading><DescriptorName UI="D000328" MajorTopicYN="N">Adult</DescriptorName></MeshHeading><MeshHeading><DescriptorName UI="D001938" MajorTopicYN="N" Type="Geographic">Brazil</DescriptorName><QualifierName UI="Q000453" MajorTopicYN="N">epidemiology</QualifierName></MeshHeading><MeshHeading><DescriptorName UI="D006760" MajorTopicYN="N">Hospitalization</DescriptorName></MeshHeading><MeshHeading><DescriptorName UI="D006801" MajorTopicYN="N">Humans</DescriptorName></MeshHeading><MeshHeading><DescriptorName UI="D007223" MajorTopicYN="N">Infant</DescriptorName></MeshHeading><MeshHeading><DescriptorName UI="D011008" MajorTopicYN="Y">Pneumococcal Infections</DescriptorName><QualifierName UI="Q000453" MajorTopicYN="N">epidemiology</QualifierName><QualifierName UI="Q000517" MajorTopicYN="N">prevention &amp; control</QualifierName></MeshHeading><MeshHeading><DescriptorName UI="D022242" MajorTopicYN="N">Pneumococcal Vaccines</DescriptorName></MeshHeading><MeshHeading><DescriptorName UI="D011014" MajorTopicYN="Y">Pneumonia</DescriptorName></MeshHeading><MeshHeading><DescriptorName UI="D018074" MajorTopicYN="N">Vaccines, Conjugate</DescriptorName></MeshHeading></MeshHeadingList><CoiStatement>Disclosure: D.M.W. is Principal Investigator on a research contract from Pfizer for studies of pneumococcal epidemiology, unrelated to this manuscript, and has received consulting fees from Pfizer, Merck, GSK, and Affinivax for work separate from this manuscript. The other authors have no conflicts to report.</CoiStatement></MedlineCitation><PubmedData><History><PubMedPubDate PubStatus="entrez"><Year>2021</Year><Month>3</Month><Day>30</Day><Hour>12</Hour><Minute>25</Minute></PubMedPubDate><PubMedPubDate PubStatus="pubmed"><Year>2021</Year><Month>3</Month><Day>31</Day><Hour>6</Hour><Minute>0</Minute></PubMedPubDate><PubMedPubDate PubStatus="medline"><Year>2021</Year><Month>6</Month><Day>1</Day><Hour>6</Hour><Minute>0</Minute></PubMedPubDate><PubMedPubDate PubStatus="pmc-release"><Year>2021</Year><Month>3</Month><Day>31</Day></PubMedPubDate></History><PublicationStatus>ppublish</PublicationStatus><ArticleIdList><ArticleId IdType="pubmed">33783394</ArticleId><ArticleId IdType="mid">NIHMS1673604</ArticleId><ArticleId IdType="pmc">PMC8011507</ArticleId><ArticleId IdType="doi">10.1097/EDE.0000000000001341</ArticleId><ArticleId IdType="pii">00001648-202105000-00008</ArticleId></ArticleIdList><ReferenceList><Reference><Citation>Schuck-Paim C, Taylor RJ, Simonsen L, et al. Challenges to estimating vaccine impact using hospitalization data. Vaccine. 2017;35:118&#x2013;124.</Citation><ArticleIdList><ArticleId IdType="pmc">PMC5664940</ArticleId><ArticleId IdType="pubmed">27899227</ArticleId></ArticleIdList></Reference><Reference><Citation>Bruhn CA, Schuck-Paim C, K&#xfc;r&#xfc;m E, Taylor RJ, Simonsen L, Weinberger DM. Improving assessments of population-level vaccine impact. Epidemiology. 2017;28:233&#x2013;236.</Citation><ArticleIdList><ArticleId IdType="pmc">PMC5285271</ArticleId><ArticleId IdType="pubmed">27922531</ArticleId></ArticleIdList></Reference><Reference><Citation>Abadie A, Diamond A, Hainmueller J. Synthetic control methods for comparative case studies: estimating the effect of California&#x2019;s tobacco control program. J Am Stat Assoc. 2010;105:493&#x2013;505.</Citation></Reference><Reference><Citation>Brodersen KH, Gallusser F, Koehler J, Remy N, Scott SL. Inferring causal impact using Bayesian structural time-series models. Ann Appl Stat. 2015;9:247&#x2013;274.</Citation></Reference><Reference><Citation>Bruhn CA, Hetterich S, Schuck-Paim C, et al. Estimating the population-level impact of vaccines using synthetic controls. Proc Natl Acad Sci U S A. 2017;114:1524&#x2013;1529.</Citation><ArticleIdList><ArticleId IdType="pmc">PMC5321019</ArticleId><ArticleId IdType="pubmed">28154145</ArticleId></ArticleIdList></Reference><Reference><Citation>Shioda K, Schuck-Paim C, Taylor RJ, et al. Challenges in estimating the impact of vaccination with sparse data. Epidemiology. 2019;30:61&#x2013;68.</Citation><ArticleIdList><ArticleId IdType="pmc">PMC6276862</ArticleId><ArticleId IdType="pubmed">30334918</ArticleId></ArticleIdList></Reference><Reference><Citation>Warren JL, Shioda K, K&#xfc;r&#xfc;m E, et al. Impact of pneumococcal conjugate vaccines against pneumonia hospitalizations in high- and low-income sub-populations in Brazil. Clin Infect Dis. 2017;65:1813&#x2013;1818.</Citation><ArticleIdList><ArticleId IdType="pmc">PMC5848248</ArticleId><ArticleId IdType="pubmed">29020195</ArticleId></ArticleIdList></Reference><Reference><Citation>Schuck-Paim C, Taylor RJ, Alonso WJ, Weinberger DM, Simonsen L. Effect of pneumococcal conjugate vaccine introduction on childhood pneumonia mortality in Brazil: a retrospective observational study. Lancet Glob Health. 2019;7:e249&#x2013;e256.</Citation><ArticleIdList><ArticleId IdType="pmc">PMC6344339</ArticleId><ArticleId IdType="pubmed">30683242</ArticleId></ArticleIdList></Reference><Reference><Citation>Carvalho CM, Polson NG, Scott JG. The horseshoe estimator for sparse signals. Biometrika. 2010;97:465&#x2013;480.</Citation></Reference><Reference><Citation>Carvalho CM, Polson NG, Scott JG. Handling sparsity via the horseshoe. 2009. In: Appearing in Proceedings of the 12th International Conference on Artificial Intelligence and Statistics (AISTATS), Clearwater Beach, FL; Volume 5 of JMLR: W&amp;CP 5.</Citation></Reference><Reference><Citation>Plummer M. rjags: Bayesian Graphical Models using MCMC. 2016. Vienna, Austria.R package version 4-6.</Citation></Reference><Reference><Citation>Geweke J. Evaluating the Accuracy of Sampling-Based Approaches to the Calculation of Posterior Moments. 1991.Vol. 196. Federal Reserve Bank of Minneapolis, Research Department Minneapolis;</Citation></Reference><Reference><Citation>Heaton MJ, Gelfand AE. Spatial regression using kernel averaged predictors. J Agric Biol Environ Stat. 2011;16:233&#x2013;252.</Citation></Reference><Reference><Citation>Heaton MJ, Gelfand AE. Kernel averaged predictors for spatio-temporal regression models. Spat Stat. 2012;2:15&#x2013;32.</Citation><ArticleIdList><ArticleId IdType="pmc">PMC3760438</ArticleId><ArticleId IdType="pubmed">24010051</ArticleId></ArticleIdList></Reference><Reference><Citation>Pugh S, Heaton MJ, Svedin J, Hansen N. Spatiotemporal lagged models for variable rate irrigation in agriculture. J Agric Biol Environ Stat. 2019;24:634&#x2013;650.</Citation></Reference><Reference><Citation>Spiegelhalter DJ, Best NG, Carlin BP, Van Der Linde A. Bayesian measures of model complexity and fit. J R Stat Soc Series B (Stat Methodol). 2002;64:583&#x2013;639.</Citation></Reference><Reference><Citation>Wagenmakers EJ, Farrell S. AIC model selection using Akaike weights. Psychon Bull Rev. 2004;11:192&#x2013;196.</Citation><ArticleIdList><ArticleId IdType="pubmed">15117008</ArticleId></ArticleIdList></Reference></ReferenceList></PubmedData></PubmedArticle></PubmedArticleSet>