{"header":{"type":"esearch","version":"0.3"},"esearchresult":{"count":"1","retmax":"0","retstart":"0","querykey":"1","webenv":"MCID_6a6033ffee0dbf9738090077","idlist":[],"translationset":[],"querytranslation":"\"Correction\"[Title] AND \"Changes\"[Title] AND \"Appropriateness\"[Title] AND \"US\"[Title] AND \"Outpatient\"[Title] AND \"Antibiotic\"[Title] AND \"Prescribing\"[Title] AND \"After\"[Title] AND \"COVID\"[Title] AND \"19\"[Title] AND \"Outbreak\"[Title] AND \"Interrupted\"[Title] AND \"Time\"[Title] AND \"series\"[Title] AND \"Analysis\"[Title] AND \"2017\"[Title] AND \"2021\"[Title] AND \"Data\"[Title]"}}
