{"header":{"type":"esearch","version":"0.3"},"esearchresult":{"count":"0","retmax":"0","retstart":"0","querykey":"1","webenv":"MCID_6a602fdcd623b302910fe4b9","idlist":[],"translationset":[],"querytranslation":"\"Estimating Influenza Vaccine Effectiveness With the Test-Negative Design Using Alternative Control Groups: A Systematic Review and Meta-Analysis\"[Title]","warninglist":{"phrasesignored":[],"quotedphrasesnotfound":["\"Estimating Influenza Vaccine Effectiveness With the Test-Negative Design Using Alternative Control Groups: A Systematic Review and Meta-Analysis\"[Title]"],"outputmessages":["No items found."]}}}
