{"header":{"type":"esearch","version":"0.3"},"esearchresult":{"count":"0","retmax":"0","retstart":"0","querykey":"1","webenv":"MCID_6a60310c449de372e10de0d3","idlist":[],"translationset":[],"querytranslation":"\"Comparison of autoregressive integrated moving average model and generalised regression neural network model for prediction of haemorrhagic fever with renal syndrome in China: a time-series study\"[Title]","warninglist":{"phrasesignored":[],"quotedphrasesnotfound":["\"Comparison of autoregressive integrated moving average model and generalised regression neural network model for prediction of haemorrhagic fever with renal syndrome in China: a time-series study\"[Title]"],"outputmessages":["No items found."]}}}
