{"header":{"type":"esearch","version":"0.3"},"esearchresult":{"count":"0","retmax":"0","retstart":"0","querykey":"1","webenv":"MCID_6a602f69bf50f4383d0a9a64","idlist":[],"translationset":[],"querytranslation":"\"Liver mortality attributable to chronic hepatitis C virus infection in Denmark and Scotland--using spontaneous resolvers as the benchmark comparator\"[Title]","warninglist":{"phrasesignored":[],"quotedphrasesnotfound":["\"Liver mortality attributable to chronic hepatitis C virus infection in Denmark and Scotland--using spontaneous resolvers as the benchmark comparator\"[Title]"],"outputmessages":["No items found."]}}}
