{
  "schema_version": 1,
  "batch_id": "W01-BATCH-024",
  "source_raw_csv_path": "01_search/search_logs/2026-07-20-broad-discovery/wave_01_frozen_queries/compiled_candidates_raw.csv",
  "source_raw_csv_sha256": "70cc6adb6ce40ed5c678ba0901cf4a23b78f64e5839304cd89002a7b19c46ec4",
  "protocol_path": "01_search/search_protocols/2026-07-20-broad-methods-discovery-protocol.md",
  "protocol_sha256": "e3b1013862e2f18314702cbf1e1e0e5c2c6b9e0d2b78113b23b9e65e2ccb20df",
  "family_precedence": [
    "causal_policy",
    "surveillance_measurement",
    "spatial_transmission",
    "forecasting_dynamics",
    "evidence_synthesis",
    "simulation_methods"
  ],
  "row_count": 150,
  "first_key": "PMID:38776389",
  "last_key": "PMID:40241736",
  "candidate_keys": [
    "PMID:38776389",
    "PMID:38785764",
    "PMID:38816865",
    "PMID:38835498",
    "PMID:38848817",
    "PMID:38870284",
    "PMID:38888768",
    "PMID:38896471",
    "PMID:38897967",
    "PMID:38902246",
    "PMID:38908389",
    "PMID:38916874",
    "PMID:38922185",
    "PMID:38927160",
    "PMID:38947052",
    "PMID:38948575",
    "PMID:38963827",
    "PMID:38978544",
    "PMID:38991457",
    "PMID:39005464",
    "PMID:39007425",
    "PMID:39026838",
    "PMID:39032914",
    "PMID:39062655",
    "PMID:39066310",
    "PMID:39087568",
    "PMID:39116677",
    "PMID:39116952",
    "PMID:39132479",
    "PMID:39138238",
    "PMID:39152215",
    "PMID:39189818",
    "PMID:39190356",
    "PMID:39190550",
    "PMID:39202123",
    "PMID:39226386",
    "PMID:39230264",
    "PMID:39234218",
    "PMID:39239568",
    "PMID:39256401",
    "PMID:39279803",
    "PMID:39284332",
    "PMID:39288612",
    "PMID:39290048",
    "PMID:39305009",
    "PMID:39312594",
    "PMID:39312727",
    "PMID:39323787",
    "PMID:39340115",
    "PMID:39349478",
    "PMID:39352417",
    "PMID:39358819",
    "PMID:39359891",
    "PMID:39373703",
    "PMID:39374437",
    "PMID:39376591",
    "PMID:39381092",
    "PMID:39415115",
    "PMID:39430599",
    "PMID:39440935",
    "PMID:39441072",
    "PMID:39446128",
    "PMID:39447143",
    "PMID:39447178",
    "PMID:39454609",
    "PMID:39457427",
    "PMID:39475466",
    "PMID:39476596",
    "PMID:39481641",
    "PMID:39493536",
    "PMID:39502171",
    "PMID:39504969",
    "PMID:39529936",
    "PMID:39530699",
    "PMID:39530777",
    "PMID:39530852",
    "PMID:39534503",
    "PMID:39546571",
    "PMID:39554028",
    "PMID:39557054",
    "PMID:39557055",
    "PMID:39565816",
    "PMID:39568452",
    "PMID:39587142",
    "PMID:39608274",
    "PMID:39611769",
    "PMID:39611833",
    "PMID:39617920",
    "PMID:39629976",
    "PMID:39630499",
    "PMID:39657433",
    "PMID:39658728",
    "PMID:39670194",
    "PMID:39676847",
    "PMID:39677427",
    "PMID:39680613",
    "PMID:39697008",
    "PMID:39700140",
    "PMID:39709561",
    "PMID:39711716",
    "PMID:39725566",
    "PMID:39737444",
    "PMID:39765616",
    "PMID:39791259",
    "PMID:39809813",
    "PMID:39818328",
    "PMID:39843962",
    "PMID:39850139",
    "PMID:39855294",
    "PMID:39864307",
    "PMID:39869938",
    "PMID:39874598",
    "PMID:39878305",
    "PMID:39890226",
    "PMID:39892000",
    "PMID:39898316",
    "PMID:39918339",
    "PMID:39922832",
    "PMID:39936851",
    "PMID:39944375",
    "PMID:39957983",
    "PMID:39958990",
    "PMID:39962182",
    "PMID:39965190",
    "PMID:39972521",
    "PMID:39984887",
    "PMID:39988586",
    "PMID:40011766",
    "PMID:40020892",
    "PMID:40023787",
    "PMID:40028458",
    "PMID:40029330",
    "PMID:40058502",
    "PMID:40066809",
    "PMID:40072967",
    "PMID:40102552",
    "PMID:40123883",
    "PMID:40133528",
    "PMID:40134787",
    "PMID:40142478",
    "PMID:40165066",
    "PMID:40165792",
    "PMID:40166569",
    "PMID:40177079",
    "PMID:40194534",
    "PMID:40196585",
    "PMID:40229304",
    "PMID:40234634",
    "PMID:40239323",
    "PMID:40241736"
  ]
}
